LICENSE
MANIFEST.in
README.md
configs.ini
pyproject.toml
setup.py
/home/saikat/Documents/work/trans-eqtl/package/tejaas-1.0.2/src/tejaas/clibs/linear_regression.c
/home/saikat/Documents/work/trans-eqtl/package/tejaas-1.0.2/src/tejaas/clibs/linear_regression_zstat.c
/home/saikat/Documents/work/trans-eqtl/package/tejaas-1.0.2/src/tejaas/clibs/reverse_regression.c
src/cpuinfo.py
src/system_info.py
src/tejaas/__init__.py
src/tejaas/main.py
src/tejaas/tester.py
src/tejaas/version.py
src/tejaas.egg-info/PKG-INFO
src/tejaas.egg-info/SOURCES.txt
src/tejaas.egg-info/dependency_links.txt
src/tejaas.egg-info/entry_points.txt
src/tejaas.egg-info/requires.txt
src/tejaas.egg-info/top_level.txt
src/tejaas/clibs/.vimrc
src/tejaas/clibs/Makefile
src/tejaas/clibs/Makefile.gwdg
src/tejaas/clibs/Makefile.minion2
src/tejaas/clibs/__init__.py
src/tejaas/clibs/linear_regression.c
src/tejaas/clibs/linear_regression_zstat.c
src/tejaas/clibs/mlpack_lasso_o.cpp
src/tejaas/clibs/npy_cblas.h
src/tejaas/clibs/npy_cblas_base.h
src/tejaas/clibs/reverse_regression.c
src/tejaas/clibs/svd.h
src/tejaas/clibs/utils.h
src/tejaas/iotools/__init__.py
src/tejaas/iotools/data.py
src/tejaas/iotools/outhandler.py
src/tejaas/iotools/readOxford.py
src/tejaas/iotools/readRPKM.py
src/tejaas/iotools/readgtf.py
src/tejaas/iotools/readgtf_v12.py
src/tejaas/iotools/readmaf.py
src/tejaas/iotools/readqnull.py
src/tejaas/iotools/readvcf.py
src/tejaas/qstats/__init__.py
src/tejaas/qstats/crrstat.py
src/tejaas/qstats/jpa.py
src/tejaas/qstats/jpa_null.py
src/tejaas/qstats/revreg.py
src/tejaas/qstats/rrstat.py
src/tejaas/qstats/zstats.py
src/tejaas/tests/__init__.py
src/tejaas/tests/test_output_files.py
src/tejaas/utils/__init__.py
src/tejaas/utils/args.py
src/tejaas/utils/cismasking.py
src/tejaas/utils/containers.py
src/tejaas/utils/knn.py
src/tejaas/utils/logs.py
src/tejaas/utils/mpihelper.py
src/tejaas/utils/mpl_stylesheet.py
src/tejaas/utils/project.py