Metadata-Version: 2.1
Name: tejaas
Version: 1.0.2
Summary: Command line tool for finding trans-eQTLs using reverse regression
Home-page: https://github.com/soedinglab/tejaas
Download-URL: https://github.com/soedinglab/tejaas
Author: Saikat Banerjee and Franco Simonetti
Author-email: bnrj.saikat@gmail.com
License: GNU GPLv3
Project-URL: Bug Tracker, https://github.com/soedinglab/tejaas/issues
Project-URL: Documentation, https://github.com/soedinglab/tejaas/wiki
Project-URL: Source Code, https://github.com/soedinglab/tejaas
Keywords: eQTL,trans-eQTL,transcriptomics,reverse regression
Classifier: Development Status :: 4 - Beta
Classifier: Intended Audience :: Education
Classifier: Intended Audience :: Science/Research
Classifier: Programming Language :: Python :: 3
Classifier: Programming Language :: Python :: 3 :: Only
Classifier: Programming Language :: Python :: 3.6
Classifier: Programming Language :: Python :: 3.7
Classifier: Programming Language :: Python :: 3.8
Classifier: Operating System :: POSIX
Classifier: Operating System :: POSIX :: Linux
Classifier: Topic :: Education
Classifier: Topic :: Scientific/Engineering :: Bio-Informatics
Classifier: License :: OSI Approved :: GNU General Public License v3 (GPLv3)
Requires-Python: >=3.6
License-File: LICENSE
